cli/__init__.py
cli/__main__.py
cli/box_storage.py
cli/config.py
cli/exceptions.py
cli/main.py
cli/safe_unpickle.py
cli/simple_hdlc.py
cli/status.py
cli/PyCRC/CRC16.py
cli/PyCRC/CRC16DNP.py
cli/PyCRC/CRC16Kermit.py
cli/PyCRC/CRC16SICK.py
cli/PyCRC/CRC32.py
cli/PyCRC/CRCCCITT.py
cli/PyCRC/__init__.py
cli/battery/__init__.py
cli/battery/battery_tui.py
cli/battery/websocket_client.py
cli/commands/__init__.py
cli/commands/box/__init__.py
cli/commands/box/boxes.py
cli/commands/box/hello.py
cli/commands/box/instruments.py
cli/commands/box/net_tui.py
cli/commands/box/nets.py
cli/commands/box/ssh.py
cli/commands/box/status/__init__.py
cli/commands/box/status/commands.py
cli/commands/box/status/status_gui.py
cli/commands/box/status/status_tui.py
cli/commands/communication/__init__.py
cli/commands/communication/ble.py
cli/commands/communication/spi.py
cli/commands/communication/uart.py
cli/commands/communication/usb.py
cli/commands/communication/websocket_client.py
cli/commands/communication/wifi.py
cli/commands/development/__init__.py
cli/commands/development/arm.py
cli/commands/development/devenv.py
cli/commands/development/python.py
cli/commands/development/debug/__init__.py
cli/commands/development/debug/commands.py
cli/commands/development/debug/gdb.py
cli/commands/development/debug/net_cache.py
cli/commands/development/debug/service_client.py
cli/commands/development/debug/service_helper.py
cli/commands/development/debug/tunnel.py
cli/commands/measurement/__init__.py
cli/commands/measurement/adc.py
cli/commands/measurement/dac.py
cli/commands/measurement/gpi.py
cli/commands/measurement/gpo.py
cli/commands/measurement/logic.py
cli/commands/measurement/scope.py
cli/commands/measurement/thermocouple.py
cli/commands/measurement/watt.py
cli/commands/power/__init__.py
cli/commands/power/battery.py
cli/commands/power/eload.py
cli/commands/power/solar.py
cli/commands/power/supply.py
cli/commands/utility/__init__.py
cli/commands/utility/binaries.py
lager_cli-0.3.18.dist-info/LICENSE
lager_cli-0.3.18.dist-info/METADATA
lager_cli-0.3.18.dist-info/WHEEL
lager_cli-0.3.18.dist-info/entry_points.txt
lager_cli-0.3.18.dist-info/top_level.txt
lager_cli-0.3.18.dist-info/RECORD
