Metadata-Version: 2.1
Name: lager-cli
Version: 0.3.18
Summary: Lager CLI - Box and Docker connectivity
Home-page: https://github.com/lagerdata/lager-mono
Author: Lager Data LLC
Author-email: hello@lagerdata.com
Maintainer: Lager Data LLC
Maintainer-email: hello@lagerdata.com
License: Apache-2.0
Classifier: Development Status :: 3 - Alpha
Classifier: License :: OSI Approved :: Apache Software License
Classifier: Programming Language :: Python :: 3
Classifier: Programming Language :: Python :: 3.10
Classifier: Programming Language :: Python :: 3.11
Classifier: Programming Language :: Python :: 3.12
Classifier: Programming Language :: Python :: 3.13
Classifier: Programming Language :: Python :: 3.14
Classifier: Topic :: Software Development
Requires-Python: >=3.10
License-File: LICENSE
Requires-Dist: async-generator>=1.10
Requires-Dist: pymongo>=4.0
Requires-Dist: certifi>=2020.6.20
Requires-Dist: chardet>=5.2.0
Requires-Dist: click>=8.1.2
Requires-Dist: colorama>=0.4.3
Requires-Dist: h11>=0.16
Requires-Dist: idna>=3.4
Requires-Dist: ipaddress>=1.0.23
Requires-Dist: Jinja2>=3.1.2
Requires-Dist: multidict>=6.0.2
Requires-Dist: outcome>=1.0.1
Requires-Dist: pigpio>=1.78
Requires-Dist: python-dateutil>=2.8.1
Requires-Dist: PyYAML>=6.0.1
Requires-Dist: requests>=2.31.0
Requires-Dist: requests-toolbelt>=1.0.0
Requires-Dist: six>=1.16.0
Requires-Dist: sniffio>=1.3.1
Requires-Dist: sortedcontainers>=2.2.2
Requires-Dist: tenacity>=6.2.0
Requires-Dist: texttable>=1.6.2
Requires-Dist: trio>=0.27.0
Requires-Dist: lager-trio-websocket>=0.9.0.dev0
Requires-Dist: urllib3<3.0.0,>=1.26.20
Requires-Dist: wsproto>=0.14.1
Requires-Dist: yarl>=1.8.1
Requires-Dist: boto3
Requires-Dist: textual>=3.2.0
Requires-Dist: python-socketio>=5.10.0
Requires-Dist: websocket-client>=1.0.0
